odoo/addons/project_tag_multicompany/README.rst
odoo/addons/project_tag_multicompany/__init__.py
odoo/addons/project_tag_multicompany/__manifest__.py
odoo/addons/project_tag_multicompany/i18n/es.po
odoo/addons/project_tag_multicompany/i18n/it.po
odoo/addons/project_tag_multicompany/i18n/project_tag_multicompany.pot
odoo/addons/project_tag_multicompany/i18n/pt_BR.po
odoo/addons/project_tag_multicompany/i18n/sv.po
odoo/addons/project_tag_multicompany/models/__init__.py
odoo/addons/project_tag_multicompany/models/project_tags.py
odoo/addons/project_tag_multicompany/readme/CONTRIBUTORS.md
odoo/addons/project_tag_multicompany/readme/DESCRIPTION.md
odoo/addons/project_tag_multicompany/security/project_tags_security.xml
odoo/addons/project_tag_multicompany/static/description/icon.png
odoo/addons/project_tag_multicompany/static/description/index.html
odoo/addons/project_tag_multicompany/views/project_tags_views.xml
odoo_addon_project_tag_multicompany-18.0.1.0.1.dist-info/METADATA
odoo_addon_project_tag_multicompany-18.0.1.0.1.dist-info/WHEEL
odoo_addon_project_tag_multicompany-18.0.1.0.1.dist-info/top_level.txt
odoo_addon_project_tag_multicompany-18.0.1.0.1.dist-info/RECORD
